toonifypy/__init__.py
toonifypy/libtoonify.dylib
toonifypy-1.1.8.dist-info/METADATA
toonifypy-1.1.8.dist-info/WHEEL
toonifypy-1.1.8.dist-info/top_level.txt
toonifypy-1.1.8.dist-info/RECORD
