Metadata-Version: 2.4
Name: toonifypy
Version: 1.1.8
Summary: High-performance JSON ↔ TOON converter. Reduce LLM token usage by 30-60% with Rust-powered Python bindings.
Home-page: https://github.com/npiesco/TOONify
Author: TOONify Contributors
Author-email: 
License: MIT
Project-URL: Bug Tracker, https://github.com/npiesco/TOONify/issues
Project-URL: Documentation, https://github.com/npiesco/TOONify#readme
Project-URL: Source Code, https://github.com/npiesco/TOONify
Keywords: toon,json,converter,llm,ai,token-optimization,rust,uniffi
Classifier: Development Status :: 4 - Beta
Classifier: Intended Audience :: Developers
Classifier: License :: OSI Approved :: MIT License
Classifier: Programming Language :: Python :: 3
Classifier: Programming Language :: Python :: 3.8
Classifier: Programming Language :: Python :: 3.9
Classifier: Programming Language :: Python :: 3.10
Classifier: Programming Language :: Python :: 3.11
Classifier: Programming Language :: Python :: 3.12
Classifier: Programming Language :: Rust
Classifier: Topic :: Software Development :: Libraries
Classifier: Topic :: Text Processing
Classifier: Operating System :: OS Independent
Requires-Python: >=3.8
Dynamic: author
Dynamic: classifier
Dynamic: description
Dynamic: description-content-type
Dynamic: home-page
Dynamic: keywords
Dynamic: license
Dynamic: project-url
Dynamic: requires-python
Dynamic: summary
